ASSIGNMENT3/ASSIGNMENT3/Gray_to_sevensegment.v
module sevenbit(input wire d2, input wire d1, input wire d0, output wire a, output b, output c, output d, output e, output f, output g );
    assign a = ~d1&~d0|~d2&d1|d2&d0;
    assign b = ~d2|~d0;
    assign c = d2 | ~d1|~d0;
    assign d = d2&d0|d1&d0|~d0&~d2;
    assign e = ~d2&~d1&~d0|d2&~d1&d0|~d2&d1&d0;
    assign f = ~d1&~d2&~d0|d2&(d1|d0);
    assign g = d1|d2&d0;
endmodule

ASSIGNMENT3/ASSIGNMENT3/Gray_to_sevensegment_tb.v
module testbench();
   reg d1,d2,d0;
     wire a,b,c,d,e,f,g;
    sevenbit inst1(.d2(d2),.d1(d1),.d0(d0),.a(a),.b(b),.c(c),.d(d),.e(e),.f(f),.g(g));
    initial begin
        $dumpfile("output.vcd");
        $dumpvars(0,testbench);
        d0=0; d1=0; d2=0; #10;
        d0=0; d1=0; d2=1; #10;
        d0=0; d1=1; d2=0; #10;
        d0=0; d1=1; d2=1; #10;
        d0=1; d1=0; d2=0; #10;
        d0=1; d1=0; d2=1; #10;
        d0=1; d1=1; d2=0; #10;
        d0=1; d1=1; d2=1; #10;
        $finish;
    end
endmodule

ASSIGNMENT3/ASSIGNMENT3/output.vcd
$date
	Sat May 30 17:07:19 2026
$end
$version
	Icarus Verilog
$end
$timescale
	1s
$end
$scope module testbench $end
$var wire 1 ! g $end
$var wire 1 " f $end
$var wire 1 # e $end
$var wire 1 $ d $end
$var wire 1 % c $end
$var wire 1 & b $end
$var wire 1 ' a $end
$var reg 1 ( d0 $end
$var reg 1 ) d1 $end
$var reg 1 * d2 $end
$scope module inst1 $end
$var wire 1 ' a $end
$var wire 1 & b $end
$var wire 1 % c $end
$var wire 1 $ d $end
$var wire 1 ( d0 $end
$var wire 1 ) d1 $end
$var wire 1 * d2 $end
$var wire 1 # e $end
$var wire 1 " f $end
$var wire 1 ! g $end
$upscope $end
$upscope $end
$enddefinitions $end
$comment Show the parameter values. $end
$dumpall
$end
#0
$dumpvars
0*
0)
0(
1'
1&
1%
1$
1#
1"
0!
$end
#10
0#
0"
0$
1*
#20
1$
1!
0*
1)
#30
0'
0$
1"
1*
#40
0"
0!
0*
0)
1(
#50
1#
1$
1'
0&
1"
1!
1*
#60
1'
1&
0%
0"
0*
1)
#70
0#
0&
1%
1"
1*
