ASSIGNMENT2/testbenches/fulladder.v
module halfadder(input a, input b,output s, output c ); 
    assign s = a^b;
    assign c = a&b;
endmodule
module fulladder(input c, input d, input cin, output finalsum, output cout );
    wire e, f ,g,h;
    assign g= cin;
    halfadder inst1(.a(c),.b(d),.s(e), .c(f));
    halfadder inst2(.a(e),.b(g),.s(finalsum), .c(h));
    assign cout = h|f;

endmodule

ASSIGNMENT2/modules/full.v
module testbench;
    reg c, d, cin; 
    wire finalsum, cout;
    fulladder inst1(.c(c),.d(d),.cin(cin),.finalsum(finalsum),.cout(cout));
    initial begin
        $dumpfile("full.vcd");
        $dumpvars(0,testbench);
        c=0; d=0; cin=0; #10;
        c=0; d=0; cin=1; #10;
        c=0; d=1; cin=0; #10;
        c=0; d=1; cin=1; #10;
        c=1; d=0; cin=0; #10;
        c=1; d=0; cin=1; #10;
        c=1; d=1; cin=0; #10;
        c=1; d=1; cin=1; #10;
        $finish;
    end
endmodule

ASSIGNMENT2/outputs/sub.vcd
$date
	Sat May 30 00:29:35 2026
$end
$version
	Icarus Verilog
$end
$timescale
	1s
$end
$scope module testbench $end
$var wire 1 ! finalsum $end
$var wire 1 " cout $end
$var reg 1 # c $end
$var reg 1 $ cin $end
$var reg 1 % d $end
$scope module inst1 $end
$var wire 1 # c $end
$var wire 1 $ cin $end
$var wire 1 " cout $end
$var wire 1 % d $end
$var wire 1 & g $end
$var wire 1 ' h $end
$var wire 1 ! finalsum $end
$var wire 1 ( f $end
$var wire 1 ) e $end
$scope module inst1 $end
$var wire 1 # a $end
$var wire 1 % b $end
$var wire 1 ( c $end
$var wire 1 ) s $end
$upscope $end
$scope module inst2 $end
$var wire 1 ) a $end
$var wire 1 & b $end
$var wire 1 ' c $end
$var wire 1 ! s $end
$upscope $end
$upscope $end
$upscope $end
$enddefinitions $end
$comment Show the parameter values. $end
$dumpall
$end
#0
$dumpvars
0)
0(
0'
0&
0%
0$
0#
0"
0!
$end
#10
1"
1!
1'
1&
1$
#20
0'
1)
1(
0&
0$
1%
#30
0!
1&
1$
#40
0"
1!
0(
0&
0$
0%
1#
#50
0!
1&
1$
#60
0)
0&
0$
1%
#70
1"
1!
1'
1&
1$
