ASSIGNMENT4/modules/alu.v
module alu(
    input [7:0] in1,
    input [7:0] in2,
    input [2:0] alu_op,
    output reg [7:0] result,
    output reg carry_flag
);
always @(*) begin
    carry_flag = 1'b0;
    case(alu_op)
        3'b000:result = ~in1;
        3'b001:result = in1&in2;
        3'b010:result = in1|in2;
        3'b011:{carry_flag,result} = in1 +in2;
        3'b100:{carry_flag,result} = in1-in2;
        3'b101:result = in1^in2;
        3'b110:{carry_flag,result} = in1+1;
        default: result = 8'b0;
    endcase
    end
endmodule

ASSIGNMENT4/modules/register.v
module register_file(
    input clk,
    input rst,
    input write_enable,
    input [3:0] write_address,
    input [7:0] write_data,
    input [3:0] read_address1,
    input [3:0] read_address2,
    output [7:0] read_data1,
    output [7:0] read_data2
);
integer i;
reg [7:0] rf [15:0];

always @(posedge clk) begin
    if (rst) begin
        for (i = 0; i < 16; i = i + 1) begin
            rf[i] <= 0;
        end
    end  else if (write_enable) begin
        rf[write_address] <= write_data;
    end
end
assign read_data1 = rf[read_address1];
assign read_data2 = rf[read_address2];
endmodule

ASSIGNMENT4/modules/bonus.v
module bonus(
    input clk,
    input rst,
    input write_enable,
    input [3:0] write_address,
    input [3:0] read_address1,
    input [3:0] read_address2,
    input [2:0] alu_op,
    input [7:0] final_write_data
); 

    wire [7:0] rf_to_alu_in1;
    wire [7:0] rf_to_alu_in2;
    wire [7:0] alu_result_out;
    wire carry_flag_out;

    register_file rf_inst (
        .clk(clk),
        .rst(rst),
        .write_enable(write_enable),
        .write_address(write_address),
        .write_data(final_write_data), 
        .read_address1(read_address1),
        .read_address2(read_address2),
        .read_data1(rf_to_alu_in1),    
        .read_data2(rf_to_alu_in2)     
    );

    alu alu_inst (
        .in1(rf_to_alu_in1),           
        .in2(rf_to_alu_in2),           
        .alu_op(alu_op),
        .result(alu_result_out),
        .carry_flag(carry_flag_out)
    );

endmodule

ASSIGNMENT4/tbs/bonustb.v
`timescale 1ns / 1ps

module tb_bonus();

    // Inputs to drive the bonus module
    reg clk;
    reg rst;
    reg write_enable;
    reg [3:0] write_address;
    reg [3:0] read_address1;
    reg [3:0] read_address2;
    reg [2:0] alu_op;
    
    // MUX Control Signals
    reg [7:0] immediate_data;
    reg use_alu_result;
    wire [7:0] final_write_data;

    // Instantiate the Unit Under Test (UUT)
    bonus uut (
        .clk(clk),
        .rst(rst),
        .write_enable(write_enable),
        .write_address(write_address),
        .read_address1(read_address1),
        .read_address2(read_address2),
        .alu_op(alu_op),
        .final_write_data(final_write_data)
    );

    // Grab the internal ALU result from inside the bonus module!
    wire [7:0] alu_result = uut.alu_result_out;
    
    // The MUX: Feed immediate data (5 or 3) OR the ALU result back to Register File
    assign final_write_data = use_alu_result ? alu_result : immediate_data;

    // Bulletproof clock generation
    initial begin
        clk = 0;
        forever #5 clk = ~clk;
    end

    // Part C Simulation Sequence
    initial begin
        $dumpfile("bonus_sim.vcd");
        $dumpvars(0, tb_bonus);

        // Initialize signals
        rst = 1; write_enable = 0; alu_op = 3'b000;
        read_address1 = 0; read_address2 = 0; write_address = 0;
        use_alu_result = 0; immediate_data = 0;
        #10 rst = 0;

        $display("--- Starting Part C Challenge via bonus.v ---");

        // Step 1: Write 5 to R1
        use_alu_result = 0;       // Use immediate data
        immediate_data = 8'd5;
        write_address = 4'd1;
        write_enable = 1;
        #10;
        
        // Step 2: Write 3 to R2
        immediate_data = 8'd3;
        write_address = 4'd2;
        #10;
        write_enable = 0;         // Turn off writing

        // Step 3 & 4: R3 = R1 + R2
        read_address1 = 4'd1;     // Output R1
        read_address2 = 4'd2;     // Output R2
        alu_op = 3'b011;          // ADD Operation
        
        #5;                       // Let combinational logic settle
        
        use_alu_result = 1;       // Flip MUX to route ALU output back in
        write_address = 4'd3;     // Destination: R3
        write_enable = 1;         // Turn writing back on
        #10;
        
        write_enable = 0;         // Turn off writing

        // Verification: Read R3 to confirm the math worked
        #10;
        read_address1 = 4'd3;
        #10;
        $display("Final Result inside R3: %d (Expected: 8)", uut.rf_to_alu_in1);

        #20 $finish;
    end
endmodule

ASSIGNMENT4/outputs/bonus_sim.vcd
$date
	Mon Jun  8 02:43:31 2026
$end
$version
	Icarus Verilog
$end
$timescale
	1ps
$end
$scope module tb_bonus $end
$var wire 8 ! alu_result [7:0] $end
$var wire 8 " final_write_data [7:0] $end
$var reg 3 # alu_op [2:0] $end
$var reg 1 $ clk $end
$var reg 8 % immediate_data [7:0] $end
$var reg 4 & read_address1 [3:0] $end
$var reg 4 ' read_address2 [3:0] $end
$var reg 1 ( rst $end
$var reg 1 ) use_alu_result $end
$var reg 4 * write_address [3:0] $end
$var reg 1 + write_enable $end
$scope module uut $end
$var wire 3 , alu_op [2:0] $end
$var wire 1 $ clk $end
$var wire 8 - final_write_data [7:0] $end
$var wire 4 . read_address1 [3:0] $end
$var wire 4 / read_address2 [3:0] $end
$var wire 1 ( rst $end
$var wire 4 0 write_address [3:0] $end
$var wire 1 + write_enable $end
$var wire 8 1 rf_to_alu_in2 [7:0] $end
$var wire 8 2 rf_to_alu_in1 [7:0] $end
$var wire 1 3 carry_flag_out $end
$var wire 8 4 alu_result_out [7:0] $end
$scope module alu_inst $end
$var wire 3 5 alu_op [2:0] $end
$var wire 8 6 in2 [7:0] $end
$var wire 8 7 in1 [7:0] $end
$var reg 1 3 carry_flag $end
$var reg 8 8 result [7:0] $end
$upscope $end
$scope module rf_inst $end
$var wire 1 $ clk $end
$var wire 4 9 read_address1 [3:0] $end
$var wire 4 : read_address2 [3:0] $end
$var wire 8 ; read_data1 [7:0] $end
$var wire 8 < read_data2 [7:0] $end
$var wire 1 ( rst $end
$var wire 4 = write_address [3:0] $end
$var wire 8 > write_data [7:0] $end
$var wire 1 + write_enable $end
$var integer 32 ? i [31:0] $end
$upscope $end
$upscope $end
$upscope $end
$enddefinitions $end
$comment Show the parameter values. $end
$dumpall
$end
#0
$dumpvars
bx ?
b0 >
b0 =
bx <
bx ;
b0 :
b0 9
bx 8
bx 7
bx 6
b0 5
bx 4
03
bx 2
bx 1
b0 0
b0 /
b0 .
b0 -
b0 ,
0+
b0 *
0)
1(
b0 '
b0 &
b0 %
0$
b0 #
b0 "
bx !
$end
#5000
b11111111 !
b11111111 4
b11111111 8
b0 2
b0 7
b0 ;
b0 1
b0 6
b0 <
b10000 ?
1$
#10000
b101 "
b101 -
b101 >
0$
1+
b1 *
b1 0
b1 =
b101 %
0(
#15000
1$
#20000
b11 "
b11 -
b11 >
0$
b10 *
b10 0
b10 =
b11 %
#25000
1$
#30000
b1000 !
b1000 4
b1000 8
0$
b11 #
b11 ,
b11 5
b11 1
b11 6
b11 <
b10 '
b10 /
b10 :
b101 2
b101 7
b101 ;
b1 &
b1 .
b1 9
0+
#35000
b1000 "
b1000 -
b1000 >
1$
1+
b11 *
b11 0
b11 =
1)
#40000
0$
#45000
1$
0+
#50000
0$
#55000
b1011 "
b1011 -
b1011 >
b1011 !
b1011 4
b1011 8
1$
b1000 2
b1000 7
b1000 ;
b11 &
b11 .
b11 9
